{
  "version": 2,
  "name": "wiki",
  "scope": "milansulc",
  "builds": [
    {
      "src": "dist/*.{css,js}",
      "use": "@now/static"
    },
    {
      "src": "favicon.ico",
      "use": "@now/static"
    },
    {
      "src": "**/*.md",
      "use": "@juicyfx/md@canary",
      "config": {
        "title": "Felix's Wiki",
        "css": [
          "/dist/theme.css",
          "https://cdnjs.cloudflare.com/ajax/libs/prism/1.16.0/themes/prism.min.css"
        ],
        "js": [
          "https://cdnjs.cloudflare.com/ajax/libs/prism/1.16.0/components/prism-core.min.js",
          "https://cdnjs.cloudflare.com/ajax/libs/prism/1.16.0/plugins/autoloader/prism-autoloader.min.js",
          "/dist/main.js"
        ]
      }
    }
  ]
}
